ffed/__init__.py
ffed/adapter.py
ffed/custom_exceptions.py
ffed/encoders_decoders/__init__.py
ffed/encoders_decoders/abstract_encoder_decoder.py
ffed/encoders_decoders/encoder_enum.py
ffed/encoders_decoders/encoders.py
ffed/encoders_decoders/tests/__init__.py
ffed/encoders_decoders/tests/base_x_test.py
ffed/encoders_decoders/tests/encoders_test.py
ffed/hashes/__init__.py
ffed/hashes/abstract_hashes.py
ffed/hashes/hashes.py
ffed/hashes/hashes_enum.py
ffed/hashes/tests/__init__.py
ffed/hashes/tests/hashes_test.py
ffed/main.py
ffed/utils.py
ffed-0.1.1.dist-info/entry_points.txt
ffed-0.1.1.dist-info/LICENSE
ffed-0.1.1.dist-info/WHEEL
ffed-0.1.1.dist-info/METADATA
ffed-0.1.1.dist-info/RECORD
